setup.py
zfx_bitbrowser/__init__.py
zfx_bitbrowser/创建浏览器_HTTP.py
zfx_bitbrowser/创建浏览器_直连.py
zfx_bitbrowser/删除所有浏览器.py
zfx_bitbrowser/删除浏览器.py
zfx_bitbrowser/启动浏览器.py
zfx_bitbrowser/填表_初始化.py
zfx_bitbrowser/获取浏览器列表.py
zfx_bitbrowser.egg-info/PKG-INFO
zfx_bitbrowser.egg-info/SOURCES.txt
zfx_bitbrowser.egg-info/dependency_links.txt
zfx_bitbrowser.egg-info/requires.txt
zfx_bitbrowser.egg-info/top_level.txt